tytan/__init__.py
tytan/_version.py
tytan/qubo.py
tytan/sampler.py
tytan-0.0.4.dist-info/LICENSE
tytan-0.0.4.dist-info/METADATA
tytan-0.0.4.dist-info/WHEEL
tytan-0.0.4.dist-info/top_level.txt
tytan-0.0.4.dist-info/RECORD
