Metadata-Version: 2.1
Name: tytan
Version: 0.0.4
Summary: QUBO Annealing SDK
Home-page: https://github.com/tytansdk/tytan
Author: Tytan Developers
Author-email: info@blueqat.com
License: Apache 2
Classifier: Programming Language :: Python :: 3
Classifier: License :: OSI Approved :: Apache Software License
Classifier: Development Status :: 3 - Alpha
License-File: LICENSE
Requires-Dist: numpy (==1.21.0)
